LICENSE
MANIFEST.in
README.rst
setup.cfg
setup.py
combinetwo.egg-info/PKG-INFO
combinetwo.egg-info/SOURCES.txt
combinetwo.egg-info/dependency_links.txt
combinetwo.egg-info/requires.txt
combinetwo.egg-info/top_level.txt
dist/combinetwo-0.0.18.tar.gz
helloworld/__init__.py
helloworld/aprint.py
helloworld/bprint.py
helloworld/cprint.py
helloworld/dprint.py
helloworld/utils/__init__.py
helloworld/utils/u_print.py