Metadata-Version: 2.1
Name: combinetwo
Version: 0.0.19
Summary: TYPE YOUR DESCRIPTION HERE
Home-page: https://github.com/Pkittipat/combinetwo.git
Author: pkittipat
Author-email: kittipat.phongsak@gmail.com
License: MIT
Keywords: CPRINT,BPRINT
Platform: UNKNOWN
Classifier: Development Status :: 3 - Alpha
Classifier: Intended Audience :: Developers
Classifier: Topic :: Software Development :: Build Tools
Classifier: License :: OSI Approved :: MIT License
Classifier: Programming Language :: Python :: 3
Classifier: Programming Language :: Python :: 3.4
Classifier: Programming Language :: Python :: 3.5
Classifier: Programming Language :: Python :: 3.6
Classifier: Programming Language :: Python :: 3.7
